fluentmap-0.1.0.dist-info/METADATA
fluentmap-0.1.0.dist-info/WHEEL
fluentmap-0.1.0.dist-info/entry_points.txt
fluentmap-0.1.0.dist-info/licenses/LICENSE
fluentmap.py
fluentmap-0.1.0.dist-info/RECORD
